Metadata-Version: 2.1
Name: oops-package
Version: 0.0
Summary: Set Operations(Union, Intersection,Minus)
Author-email: raghavshetty319@gmail.com
